verysimplemodule_0731_2021/__init__.py
verysimplemodule_0731_2021/add.py
verysimplemodule_0731_2021/substract.py
verysimplemodule_0731_2021/extras/__init__.py
verysimplemodule_0731_2021-0.0.1.dist-info/METADATA
verysimplemodule_0731_2021-0.0.1.dist-info/WHEEL
verysimplemodule_0731_2021-0.0.1.dist-info/top_level.txt
verysimplemodule_0731_2021-0.0.1.dist-info/RECORD
